aldryn_mailchimp/__init__.py
aldryn_mailchimp/admin.py
aldryn_mailchimp/cms_app.py
aldryn_mailchimp/cms_plugins.py
aldryn_mailchimp/forms.py
aldryn_mailchimp/models.py
aldryn_mailchimp/urls.py
aldryn_mailchimp/utils.py
aldryn_mailchimp/views.py
aldryn_mailchimp/locale/de/LC_MESSAGES/django.mo
aldryn_mailchimp/locale/de/LC_MESSAGES/django.po
aldryn_mailchimp/locale/en/LC_MESSAGES/django.mo
aldryn_mailchimp/locale/en/LC_MESSAGES/django.po
aldryn_mailchimp/management/__init__.py
aldryn_mailchimp/management/commands/__init__.py
aldryn_mailchimp/management/commands/fetch_campaigns.py
aldryn_mailchimp/migrations/0001_initial.py
aldryn_mailchimp/migrations/0002_auto__chg_field_subscriptionplugin_list_id.py
aldryn_mailchimp/migrations/0003_remove_apphook__rename_plugin.py
aldryn_mailchimp/migrations/0004_auto__add_field_subscriptionplugin_assign_language.py
aldryn_mailchimp/migrations/0005_fix_old_cmsplugin_tables.py
aldryn_mailchimp/migrations/0006_auto__add_campaign__add_selectedcampaignsplugin__add_campaignarchivepl.py
aldryn_mailchimp/migrations/0007_auto__add_category__add_keyword__add_field_campaign_category__chg_fiel.py
aldryn_mailchimp/migrations/0008_auto__add_field_category_order__add_field_keyword_order__chg_field_key.py
aldryn_mailchimp/migrations/0009_auto__add_field_campaign_display_name.py
aldryn_mailchimp/migrations/__init__.py
aldryn_mailchimp/templates/.DS_Store
aldryn_mailchimp/templates/aldryn_mailchimp/base.html
aldryn_mailchimp/templates/aldryn_mailchimp/campaign_detail.html
aldryn_mailchimp/templates/aldryn_mailchimp/campaign_detail_iframe.html
aldryn_mailchimp/templates/aldryn_mailchimp/campaign_list.html
aldryn_mailchimp/templates/aldryn_mailchimp/subscription.html
aldryn_mailchimp/templates/aldryn_mailchimp/includes/campaign_list.html
aldryn_mailchimp/templates/aldryn_mailchimp/plugins/campaign_archive.html
aldryn_mailchimp/templates/aldryn_mailchimp/plugins/selected_campaigns.html
aldryn_mailchimp-0.2.5.dist-info/DESCRIPTION.rst
aldryn_mailchimp-0.2.5.dist-info/METADATA
aldryn_mailchimp-0.2.5.dist-info/metadata.json
aldryn_mailchimp-0.2.5.dist-info/RECORD
aldryn_mailchimp-0.2.5.dist-info/top_level.txt
aldryn_mailchimp-0.2.5.dist-info/WHEEL
